testbankpackage/__init__.py
testbankpackage/functions.py
test_bank_package-0.1.0.dist-info/LICENSE
test_bank_package-0.1.0.dist-info/METADATA
test_bank_package-0.1.0.dist-info/WHEEL
test_bank_package-0.1.0.dist-info/top_level.txt
test_bank_package-0.1.0.dist-info/RECORD
