Metadata-Version: 2.1
Name: test-bank-package
Version: 0.1.0
Summary: This is a test package for Bank
Requires-Python: >=3.10
License-File: LICENSE
Requires-Dist: uv==0.5.4
